{
  "response_code": 0,
  "results": [
    {
      "type": "multiple",
      "difficulty": "easy",
      "category": "Science &amp; Nature",
      "question": "What is the chemical makeup of water?",
      "correct_answer": "H20",
      "incorrect_answers": [
        "C12H6O2",
        "CO2",
        "H"
      ]
    },
    {
      "type": "multiple",
      "difficulty": "medium",
      "category": "Entertainment: Video Games",
      "question": "In Terraria, which of these items is NOT crafted at a Mythril Anvil?",
      "correct_answer": "Ankh Charm",
      "incorrect_answers": [
        "Venom Staff",
        "Sky Fracture",
        "Orichalcum Tools"
      ]
    },
    {
      "type": "multiple",
      "difficulty": "medium",
      "category": "Sports",
      "question": "Which Formula One driver was nicknamed &#039;The Professor&#039;?",
      "correct_answer": "Alain Prost",
      "incorrect_answers": [
        "Ayrton Senna",
        "Niki Lauda",
        "Emerson Fittipaldi"
      ]
    },
    {
      "type": "multiple",
      "difficulty": "medium",
      "category": "Entertainment: Musicals &amp; Theatres",
      "question": "In which Shakespearean play will you find the suicide of Ophelia?",
      "correct_answer": "Hamlet",
      "incorrect_answers": [
        "Macbeth",
        "Othello",
        "King Lear"
      ]
    },
    {
      "type": "multiple",
      "difficulty": "hard",
      "category": "Politics",
      "question": "What year did the effort to deploy the Common Core State Standards (CCSS) in the US begin?",
      "correct_answer": "2009",
      "incorrect_answers": [
        "2012",
        "2006",
        "1997"
      ]
    },
    {
      "type": "multiple",
      "difficulty": "medium",
      "category": "History",
      "question": "The Korean War started in what year?",
      "correct_answer": "1950",
      "incorrect_answers": [
        "1945",
        "1960",
        "1912"
      ]
    },
    {
      "type": "multiple",
      "difficulty": "hard",
      "category": "Entertainment: Music",
      "question": "Which member of the English band &quot;The xx&quot; released their solo album &quot;In Colour&quot; in 2015?",
      "correct_answer": "Jamie xx",
      "incorrect_answers": [
        "Romy Madley Croft",
        "Oliver Sim",
        "Baria Qureshi"
      ]
    },
    {
      "type": "multiple",
      "difficulty": "hard",
      "category": "Entertainment: Video Games",
      "question": "What was the world&#039;s first handheld game device?",
      "correct_answer": "Mattel Auto Race",
      "incorrect_answers": [
        "Game Boy",
        "Microvision",
        "Game &amp; Watch"
      ]
    },
    {
      "type": "multiple",
      "difficulty": "medium",
      "category": "General Knowledge",
      "question": "Which of the General Mills Corporation&#039;s monster cereals was the last to be released in the 1970&#039;s?",
      "correct_answer": "Fruit Brute",
      "incorrect_answers": [
        "Count Chocula",
        "Franken Berry",
        "Boo-Berry"
      ]
    },
    {
      "type": "multiple",
      "difficulty": "hard",
      "category": "Entertainment: Music",
      "question": "The heavy metal band Black Sabbath hail from which English city?",
      "correct_answer": "Birmingham",
      "incorrect_answers": [
        "Manchester",
        "London",
        "Newcastle-Upon-Tyne"
      ]
    },
    {
      "type": "multiple",
      "difficulty": "medium",
      "category": "Entertainment: Music",
      "question": "According to the RIAA: Which artist has sold the most albums by the million?",
      "correct_answer": "The Beatles",
      "incorrect_answers": [
        "Elvis Presley",
        "Michael Jackson",
        "Pink Floyd"
      ]
    },
    {
      "type": "multiple",
      "difficulty": "easy",
      "category": "Celebrities",
      "question": "Which celebrity announced his presidency in 2015?",
      "correct_answer": "Kanye West",
      "incorrect_answers": [
        "Donald Trump",
        "Leonardo DiCaprio",
        "Miley Cyrus"
      ]
    },
    {
      "type": "multiple",
      "difficulty": "medium",
      "category": "Entertainment: Video Games",
      "question": "In Forza Motorsport 6, which of these track-exclusive cars was NOT featured in the game, either originally with the game or added as DLC?",
      "correct_answer": "Aston Martin Vulcan",
      "incorrect_answers": [
        "Ferrari FXX-K",
        "McLaren P1 GTR",
        "Lotus E23"
      ]
    },
    {
      "type": "multiple",
      "difficulty": "medium",
      "category": "Entertainment: Film",
      "question": "Who voiced Metalbeard in &quot;The Lego Movie&quot;?",
      "correct_answer": "Nick Offerman",
      "incorrect_answers": [
        "Liam Neeson",
        "Morgan Freeman",
        "Will Arnet"
      ]
    },
    {
      "type": "multiple",
      "difficulty": "easy",
      "category": "History",
      "question": "How long did World War II last?",
      "correct_answer": "6 years",
      "incorrect_answers": [
        "4 years",
        "5 years",
        "7 years"
      ]
    },
    {
      "type": "multiple",
      "difficulty": "easy",
      "category": "Science &amp; Nature",
      "question": "This element, when overcome with extreme heat and pressure, creates diamonds.",
      "correct_answer": "Carbon",
      "incorrect_answers": [
        "Nitrogen",
        "Oxygen",
        "Hydrogen"
      ]
    },
    {
      "type": "multiple",
      "difficulty": "easy",
      "category": "Science &amp; Nature",
      "question": "Which element has the chemical symbol &#039;Fe&#039;?",
      "correct_answer": "Iron",
      "incorrect_answers": [
        "Gold",
        "Silver",
        "Tin"
      ]
    },
    {
      "type": "multiple",
      "difficulty": "medium",
      "category": "General Knowledge",
      "question": "Where does water from Poland Spring water bottles come from?",
      "correct_answer": "Maine, United States",
      "incorrect_answers": [
        "Hesse, Germany",
        "Masovia, Poland",
        "Bavaria, Poland"
      ]
    },
    {
      "type": "multiple",
      "difficulty": "easy",
      "category": "Entertainment: Japanese Anime &amp; Manga",
      "question": "Who is the true moon princess in Sailor Moon?",
      "correct_answer": "Sailor Moon",
      "incorrect_answers": [
        "Sailor Venus",
        "Sailor Mars",
        "Sailor Jupiter"
      ]
    },
    {
      "type": "multiple",
      "difficulty": "hard",
      "category": "General Knowledge",
      "question": "What is the most commonly used noun in the English language?",
      "correct_answer": "Time",
      "incorrect_answers": [
        "Home",
        "Water",
        "Man"
      ]
    },
    {
      "type": "multiple",
      "difficulty": "medium",
      "category": "Geography",
      "question": "Where is Hadrian&#039;s Wall located?",
      "correct_answer": "Carlisle, England",
      "incorrect_answers": [
        "Rome, Italy",
        "Alexandria, Egypt",
        "Dublin, Ireland"
      ]
    },
    {
      "type": "multiple",
      "difficulty": "medium",
      "category": "Entertainment: Music",
      "question": "Pink Floyd made this song for their previous lead singer Syd Barrett.",
      "correct_answer": "Shine On You Crazy Diamond",
      "incorrect_answers": [
        "Wish You Were Here",
        "Have A Cigar",
        "Welcome to the Machine"
      ]
    },
    {
      "type": "multiple",
      "difficulty": "hard",
      "category": "Entertainment: Video Games",
      "question": "In the game Warframe, what Mastery Rank do you need to have to build the Tigris Prime?",
      "correct_answer": "13",
      "incorrect_answers": [
        "6",
        "18",
        "10"
      ]
    },
    {
      "type": "multiple",
      "difficulty": "easy",
      "category": "Vehicles",
      "question": "Which car tire manufacturer is famous for its &quot;Eagle&quot; brand of tires, and is the official tire supplier of NASCAR?",
      "correct_answer": "Goodyear",
      "incorrect_answers": [
        "Pirelli",
        "Bridgestone",
        "Michelin"
      ]
    },
    {
      "type": "multiple",
      "difficulty": "medium",
      "category": "Science &amp; Nature",
      "question": "An organism described as &quot;heliotropic&quot; has a tendancy to move towards which of these things?",
      "correct_answer": "Light",
      "incorrect_answers": [
        "Water",
        "Trees",
        "Pollen"
      ]
    },
    {
      "type": "multiple",
      "difficulty": "easy",
      "category": "Animals",
      "question": "What is the scientific name for modern day humans?",
      "correct_answer": "Homo Sapiens",
      "incorrect_answers": [
        "Homo Ergaster",
        "Homo Erectus",
        "Homo Neanderthalensis"
      ]
    },
    {
      "type": "multiple",
      "difficulty": "hard",
      "category": "Entertainment: Video Games",
      "question": "What vault in the video game &quot;Fallout 3&quot; is the home of multiple clones named Gary?",
      "correct_answer": "Vault 108",
      "incorrect_answers": [
        "Vault 101",
        "Vault 87",
        "Vault 21"
      ]
    },
    {
      "type": "multiple",
      "difficulty": "medium",
      "category": "Entertainment: Video Games",
      "question": "What is the AK-47&#039;s name in Counter Strike: Source?",
      "correct_answer": "CV-47",
      "incorrect_answers": [
        "AK-74",
        "AK",
        "CZ-75"
      ]
    },
    {
      "type": "multiple",
      "difficulty": "easy",
      "category": "General Knowledge",
      "question": "In DC comics where does the Green Arrow (Oliver Queen) live?",
      "correct_answer": "Star City",
      "incorrect_answers": [
        "Central City",
        "Gotham City",
        "Metropolis"
      ]
    },
    {
      "type": "multiple",
      "difficulty": "medium",
      "category": "Sports",
      "question": "How many scoring zones are there on a conventional dart board?",
      "correct_answer": "82",
      "incorrect_answers": [
        "62",
        "42",
        "102"
      ]
    },
    {
      "type": "multiple",
      "difficulty": "medium",
      "category": "Science &amp; Nature",
      "question": "What is the molecular formula of the active component of chili peppers(Capsaicin)?",
      "correct_answer": "C18H27NO3",
      "incorrect_answers": [
        "C21H23NO3",
        "C6H4Cl2",
        "C13H25NO4"
      ]
    },
    {
      "type": "multiple",
      "difficulty": "easy",
      "category": "Sports",
      "question": "How many soccer players should be on the field at the same time?",
      "correct_answer": "22",
      "incorrect_answers": [
        "20",
        "24",
        "26"
      ]
    },
    {
      "type": "multiple",
      "difficulty": "medium",
      "category": "History",
      "question": "Which of the following Presidents of the United States was assassinated?",
      "correct_answer": "William McKinley",
      "incorrect_answers": [
        "Lyndon Johnson",
        "Chester Arthur",
        "Franklin Roosevelt"
      ]
    },
    {
      "type": "multiple",
      "difficulty": "medium",
      "category": "General Knowledge",
      "question": "On average, Americans consume 100 pounds of what per second?",
      "correct_answer": "Chocolate",
      "incorrect_answers": [
        "Potatoes",
        "Donuts",
        "Cocaine"
      ]
    },
    {
      "type": "multiple",
      "difficulty": "easy",
      "category": "Entertainment: Video Games",
      "question": "Which Pok&eacute;mon can learn the move &quot;Secret Power&quot; by leveling up?",
      "correct_answer": "Audino",
      "incorrect_answers": [
        "Type:Null",
        "Arceus",
        "Silvally"
      ]
    },
    {
      "type": "multiple",
      "difficulty": "medium",
      "category": "History",
      "question": "Which U.S. President was famously &#039;attacked&#039; by a swimming rabbit?",
      "correct_answer": "Jimmy Carter",
      "incorrect_answers": [
        "Ronald Reagan",
        "Lydon B. Johnson",
        "Gerald Ford"
      ]
    },
    {
      "type": "multiple",
      "difficulty": "medium",
      "category": "Entertainment: Music",
      "question": "What genre of EDM is the Dutch DJ, musician, and remixer Armin van Buuren most well-known for?",
      "correct_answer": "Trance",
      "incorrect_answers": [
        "House",
        "Drum and Bass",
        "Dubstep"
      ]
    },
    {
      "type": "multiple",
      "difficulty": "easy",
      "category": "History",
      "question": "Who was the first ruler of Haiti after the country had gained its independence?",
      "correct_answer": "Jean-Jacques Dessalines",
      "incorrect_answers": [
        "Toussaint Louverture",
        "Henri Christophe",
        "Alexandre Petion"
      ]
    },
    {
      "type": "multiple",
      "difficulty": "hard",
      "category": "Entertainment: Board Games",
      "question": "Which of these cards from &quot;Magic: The Gathering&quot; has a flavor text that begins with &quot;Oi oi oi&quot;?",
      "correct_answer": "Uthden Troll",
      "incorrect_answers": [
        "Lotleth Troll",
        "Albino Troll",
        "Harvester Troll"
      ]
    },
    {
      "type": "multiple",
      "difficulty": "easy",
      "category": "Entertainment: Television",
      "question": "What was the name of the police officer in the cartoon &quot;Top Cat&quot;?",
      "correct_answer": "Dibble",
      "incorrect_answers": [
        "Barbrady",
        "Mahoney",
        "Murphy"
      ]
    },
    {
      "type": "multiple",
      "difficulty": "medium",
      "category": "Mythology",
      "question": "What animal did Queen Pasipahe sleep with before she gave birth to the Minotaur in Greek Mythology?",
      "correct_answer": "Bull",
      "incorrect_answers": [
        "Pig",
        "Ox",
        "Horse"
      ]
    },
    {
      "type": "multiple",
      "difficulty": "easy",
      "category": "Entertainment: Television",
      "question": "In the Star Trek universe, what color is Vulcan blood?",
      "correct_answer": "Green",
      "incorrect_answers": [
        "Blue",
        "Red",
        "Purple"
      ]
    },
    {
      "type": "multiple",
      "difficulty": "medium",
      "category": "Geography",
      "question": "What is the capital of Chile?",
      "correct_answer": "Santiago",
      "incorrect_answers": [
        "Valpara&iacute;so",
        "Copiap&oacute;",
        "Antofagasta"
      ]
    },
    {
      "type": "multiple",
      "difficulty": "easy",
      "category": "Science: Gadgets",
      "question": "The term &quot;battery&quot; to describe an electrical storage device was coined by?",
      "correct_answer": "Benjamin Franklin",
      "incorrect_answers": [
        "Nikola Tesla",
        "Luigi Galvani",
        " Alessandro Volta"
      ]
    },
    {
      "type": "multiple",
      "difficulty": "medium",
      "category": "History",
      "question": "Which country had an &quot;Orange Revolution&quot; between 2004 and 2005?",
      "correct_answer": "Ukraine",
      "incorrect_answers": [
        "Belarus",
        "Latvia",
        "Lithuania"
      ]
    },
    {
      "type": "multiple",
      "difficulty": "medium",
      "category": "Entertainment: Film",
      "question": "What film did James Cameron&#039;s Avatar dethrone as the highest-grossing film ever?",
      "correct_answer": "Titanic",
      "incorrect_answers": [
        "Star Wars",
        "Gone with the Wind",
        "Jaws"
      ]
    },
    {
      "type": "multiple",
      "difficulty": "easy",
      "category": "History",
      "question": "Which famous military commander marched an army, which included war elephants, over the Alps during the Second Punic War?",
      "correct_answer": "Hannibal",
      "incorrect_answers": [
        "Garmanicus",
        "Alexander the Great",
        "Tiberius"
      ]
    },
    {
      "type": "multiple",
      "difficulty": "easy",
      "category": "Entertainment: Japanese Anime &amp; Manga",
      "question": "Who was given the title &quot;Full Metal&quot; in the anime series &quot;Full Metal Alchemist&quot;?",
      "correct_answer": "Edward Elric",
      "incorrect_answers": [
        "Alphonse Elric",
        "Van Hohenheim",
        "Izumi Curtis"
      ]
    },
    {
      "type": "multiple",
      "difficulty": "easy",
      "category": "Science &amp; Nature",
      "question": "What is the common name of the chemical compound &quot;dihydrogen monoxide&quot;?",
      "correct_answer": "Water",
      "incorrect_answers": [
        "Methane",
        "Ammonia ",
        "Laughing Gas"
      ]
    },
    {
      "type": "multiple",
      "difficulty": "easy",
      "category": "Science: Computers",
      "question": "The programming language &#039;Swift&#039; was created to replace what other programming language?",
      "correct_answer": "Objective-C",
      "incorrect_answers": [
        "C#",
        "Ruby",
        "C++"
      ]
    }
  ]
}