{
  "response_code": 0,
  "results": [
    {
      "type": "multiple",
      "difficulty": "hard",
      "category": "Science &amp; Nature",
      "question": "The core of the Sun can reach which temperature?",
      "correct_answer": "27&deg; Million F (15&deg; Million C)",
      "incorrect_answers": [
        "938,000&deg; F (521093.3&deg; C)",
        "8&deg; Billion F (&deg;4.4 Billion C)",
        "Absolute Zero (Both F and C)"
      ]
    },
    {
      "type": "multiple",
      "difficulty": "easy",
      "category": "General Knowledge",
      "question": "When was the Playstation 3 released?",
      "correct_answer": "November 11, 2006",
      "incorrect_answers": [
        "January 8, 2007",
        "December 25, 2007",
        "July 16, 2006"
      ]
    },
    {
      "type": "multiple",
      "difficulty": "easy",
      "category": "Entertainment: Video Games",
      "question": "In the game &quot;Hearthstone&quot;, what is the best rank possible?",
      "correct_answer": "Rank 1 Legend",
      "incorrect_answers": [
        "Rank 1 Elite",
        "Rank 1 Master",
        "Rank 1 Supreme"
      ]
    },
    {
      "type": "multiple",
      "difficulty": "medium",
      "category": "Entertainment: Video Games",
      "question": "Which one of the following actors did not voice a character in &quot;Saints Row: The Third&quot;?",
      "correct_answer": "Ron Jeremy",
      "incorrect_answers": [
        "Sasha Grey",
        "Burt Reynolds",
        "Hulk Hogan"
      ]
    },
    {
      "type": "multiple",
      "difficulty": "easy",
      "category": "Entertainment: Television",
      "question": "Who played Agent Fox Mulder in the TV sci-fi drama &quot;The X-Files&quot;?",
      "correct_answer": "David Duchovny",
      "incorrect_answers": [
        "Gillian Anderson",
        "Robert Patrick",
        "Mitch Pileggi"
      ]
    },
    {
      "type": "multiple",
      "difficulty": "medium",
      "category": "Entertainment: Television",
      "question": "Who composed the theme song for The Simpsons?",
      "correct_answer": "Danny Elfman",
      "incorrect_answers": [
        "John Williams",
        "Hans Zimmer",
        "Ennio Morricone"
      ]
    },
    {
      "type": "multiple",
      "difficulty": "easy",
      "category": "Entertainment: Cartoon &amp; Animations",
      "question": "In the Pixar film, &quot;Toy Story&quot; what was the name of the child who owned the toys?",
      "correct_answer": "Andy",
      "incorrect_answers": [
        "Edward",
        "Danny",
        "Matt"
      ]
    },
    {
      "type": "multiple",
      "difficulty": "medium",
      "category": "Celebrities",
      "question": "What caused Jake Lloyd who played Anakin Skywalker in The Phantom Menace to quit acting?",
      "correct_answer": "Bullying",
      "incorrect_answers": [
        "Criminal Record",
        "Nomination for Worst Actor",
        "Racism"
      ]
    },
    {
      "type": "multiple",
      "difficulty": "easy",
      "category": "Entertainment: Television",
      "question": "Which of the following won the first season of American Idol in 2002?",
      "correct_answer": "Kelly Clarkson",
      "incorrect_answers": [
        "Justin Guarini",
        "Ruben Studdard",
        "Chris Daughtry"
      ]
    },
    {
      "type": "multiple",
      "difficulty": "medium",
      "category": "History",
      "question": "Which of the following Assyrian kings did NOT rule during the Neo-Assyrian Empire?",
      "correct_answer": "Shamshi-Adad III",
      "incorrect_answers": [
        "Shalmaneser V",
        "Esharhaddon",
        "Ashur-nasir-pal II"
      ]
    },
    {
      "type": "multiple",
      "difficulty": "hard",
      "category": "Entertainment: Video Games",
      "question": "Which of the four empires in  Eve Online was the first to achieve faster than light travel?",
      "correct_answer": "Amarr Empire",
      "incorrect_answers": [
        "Caldari State",
        "Gallente Federation",
        "Minmatar Republic"
      ]
    },
    {
      "type": "multiple",
      "difficulty": "medium",
      "category": "History",
      "question": "Who is attributed credit for recording the epic poem The Odyssey?",
      "correct_answer": "Homer",
      "incorrect_answers": [
        "Aristotle",
        "Odysseus",
        "Socrates"
      ]
    },
    {
      "type": "multiple",
      "difficulty": "hard",
      "category": "Science &amp; Nature",
      "question": "In quantum physics, which of these theorised sub-atomic particles has yet to be observed?",
      "correct_answer": "Graviton",
      "incorrect_answers": [
        "Z boson",
        "Tau neutrino",
        "Gluon"
      ]
    },
    {
      "type": "multiple",
      "difficulty": "medium",
      "category": "Science: Mathematics",
      "question": "To the nearest whole number, how many radians are in a whole circle?",
      "correct_answer": "6",
      "incorrect_answers": [
        "3",
        "4",
        "5"
      ]
    },
    {
      "type": "multiple",
      "difficulty": "easy",
      "category": "Celebrities",
      "question": "Neil Hamburger is played by which comedian?",
      "correct_answer": "Gregg Turkington",
      "incorrect_answers": [
        "Nathan Fielder",
        "Tim Heidecker",
        "Todd Glass"
      ]
    },
    {
      "type": "multiple",
      "difficulty": "easy",
      "category": "Science &amp; Nature",
      "question": "The biggest distinction between a eukaryotic cell and a prokaryotic cell is:",
      "correct_answer": "The presence or absence of a nucleus",
      "incorrect_answers": [
        "The overall size",
        "The presence or absence of certain organelles",
        "The mode of reproduction"
      ]
    },
    {
      "type": "multiple",
      "difficulty": "hard",
      "category": "History",
      "question": "Which English king was married to Eleanor of Aquitaine?",
      "correct_answer": "Henry II",
      "incorrect_answers": [
        "Richard I",
        "Henry I",
        "Henry V"
      ]
    },
    {
      "type": "multiple",
      "difficulty": "medium",
      "category": "History",
      "question": "The creator of the Enigma Cypher and Machine was of what nationality?",
      "correct_answer": "German",
      "incorrect_answers": [
        "American",
        "British",
        "Polish"
      ]
    },
    {
      "type": "multiple",
      "difficulty": "medium",
      "category": "Entertainment: Video Games",
      "question": "In Forza Motorsport 6, which of these track-exclusive cars was NOT featured in the game, either originally with the game or added as DLC?",
      "correct_answer": "Aston Martin Vulcan",
      "incorrect_answers": [
        "Ferrari FXX-K",
        "McLaren P1 GTR",
        "Lotus E23"
      ]
    },
    {
      "type": "multiple",
      "difficulty": "hard",
      "category": "Mythology",
      "question": "According to Algonquian folklore, how does one transform into a Wendigo?",
      "correct_answer": "Participating in cannibalism.",
      "incorrect_answers": [
        "Excessive mutilation of animal corpses.",
        "Performing a ritual involving murder.",
        "Drinking the blood of many slain animals."
      ]
    },
    {
      "type": "multiple",
      "difficulty": "easy",
      "category": "Entertainment: Television",
      "question": "In the show Stranger Things, what is Eleven&#039;s favorite breakfast food?",
      "correct_answer": "Eggo Waffles",
      "incorrect_answers": [
        "Toast",
        "Captain Crunch",
        "Bacon and Eggs"
      ]
    },
    {
      "type": "multiple",
      "difficulty": "easy",
      "category": "General Knowledge",
      "question": "When someone is cowardly, they are said to have what color belly?",
      "correct_answer": "Yellow",
      "incorrect_answers": [
        "Green",
        "Red",
        "Blue"
      ]
    },
    {
      "type": "multiple",
      "difficulty": "easy",
      "category": "Entertainment: Video Games",
      "question": "When was Minecraft first released to the public?",
      "correct_answer": "May 17th, 2009",
      "incorrect_answers": [
        "September 17th, 2009",
        "November 18th, 2011",
        "October 7th, 2011"
      ]
    },
    {
      "type": "multiple",
      "difficulty": "medium",
      "category": "History",
      "question": "In what year did Kentucky become the 15th state to join the union?",
      "correct_answer": "1792",
      "incorrect_answers": [
        "1782",
        "1798",
        "1788"
      ]
    },
    {
      "type": "multiple",
      "difficulty": "medium",
      "category": "History",
      "question": "What number does the Roman numeral &quot;D&quot; stand for?",
      "correct_answer": "500",
      "incorrect_answers": [
        "100",
        "1000",
        "50"
      ]
    },
    {
      "type": "multiple",
      "difficulty": "easy",
      "category": "General Knowledge",
      "question": "Which country, not including Japan, has the most people of Japanese descent?",
      "correct_answer": "Brazil",
      "incorrect_answers": [
        "China",
        "South Korea",
        "United States of America"
      ]
    },
    {
      "type": "multiple",
      "difficulty": "medium",
      "category": "Geography",
      "question": "How many sovereign states are members of the United Nations?",
      "correct_answer": "195",
      "incorrect_answers": [
        "201",
        "153",
        "178"
      ]
    },
    {
      "type": "multiple",
      "difficulty": "easy",
      "category": "Entertainment: Video Games",
      "question": "Which of the following is NOT one of the main characters in Grand Theft Auto V&rsquo;s story mode?",
      "correct_answer": "Tommy Vercetti",
      "incorrect_answers": [
        "Michael de Santa",
        "Franklin Clinton",
        "Trevor Phillips"
      ]
    },
    {
      "type": "multiple",
      "difficulty": "easy",
      "category": "Entertainment: Video Games",
      "question": "In World of Warcraft the default UI color that signifies Druid is what?",
      "correct_answer": "Orange",
      "incorrect_answers": [
        "Brown",
        "Green",
        "Blue"
      ]
    },
    {
      "type": "multiple",
      "difficulty": "easy",
      "category": "Science &amp; Nature",
      "question": "What organelle aids in synthesis of DNA in cells?",
      "correct_answer": "Ribosomes",
      "incorrect_answers": [
        "Nuclei",
        "Lysosomes",
        "Mitochondria"
      ]
    },
    {
      "type": "multiple",
      "difficulty": "hard",
      "category": "History",
      "question": "What year was Canada founded in?",
      "correct_answer": "1867",
      "incorrect_answers": [
        "1798",
        "1859",
        "1668"
      ]
    },
    {
      "type": "multiple",
      "difficulty": "hard",
      "category": "Science &amp; Nature",
      "question": "What is the name for the auditory illusion of a note that seems to be rising infinitely?",
      "correct_answer": "Shepard Tone",
      "incorrect_answers": [
        "Glissandro Illusion",
        "Fransen Effect",
        "McGurck Effect"
      ]
    },
    {
      "type": "multiple",
      "difficulty": "medium",
      "category": "History",
      "question": "What is the name of the US Navy spy ship which was attacked and captured by North Korean forces in 1968?",
      "correct_answer": "USS Pueblo",
      "incorrect_answers": [
        "USS North Carolina",
        "USS Constitution",
        "USS Indianapolis"
      ]
    },
    {
      "type": "multiple",
      "difficulty": "easy",
      "category": "General Knowledge",
      "question": "What is the official language of Brazil?",
      "correct_answer": "Portuguese",
      "incorrect_answers": [
        "Brazilian",
        "Spanish",
        "English"
      ]
    },
    {
      "type": "multiple",
      "difficulty": "medium",
      "category": "Entertainment: Film",
      "question": "Which of these Disney classics was released in 1970?",
      "correct_answer": "The Aristocats",
      "incorrect_answers": [
        "One Hundred and One Dalmatians",
        "The Fox and the Hound",
        "The Little Mermaid"
      ]
    },
    {
      "type": "multiple",
      "difficulty": "medium",
      "category": "General Knowledge",
      "question": "The Mexican Beer &quot;Corona&quot; is what type of beer?",
      "correct_answer": "Pale Lager",
      "incorrect_answers": [
        "India Pale Ale",
        "Pilfsner",
        "Baltic Porter"
      ]
    },
    {
      "type": "multiple",
      "difficulty": "easy",
      "category": "Entertainment: Video Games",
      "question": "In &quot;Call Of Duty: Zombies&quot;, what is the name of the machine that upgrades weapons?",
      "correct_answer": "Pack-A-Punch",
      "incorrect_answers": [
        "Wunderfizz",
        "Gersch Device",
        "Mule Kick"
      ]
    },
    {
      "type": "multiple",
      "difficulty": "hard",
      "category": "Entertainment: Music",
      "question": "On which Beatles album would you find the song &#039;Eleanor Rigby&#039;?",
      "correct_answer": "Revolver",
      "incorrect_answers": [
        "Help!",
        "Rubber Soul",
        "Abbey Road"
      ]
    },
    {
      "type": "multiple",
      "difficulty": "easy",
      "category": "Sports",
      "question": "Who won the UEFA Champions League in 2017?",
      "correct_answer": "Real Madrid C.F.",
      "incorrect_answers": [
        "Atletico Madrid",
        "AS Monaco FC",
        "Juventus F.C."
      ]
    },
    {
      "type": "multiple",
      "difficulty": "hard",
      "category": "Entertainment: Video Games",
      "question": "Which Kingdom Hearts game featured the cast of &quot;The World Ends With You&quot;?",
      "correct_answer": "Dream Drop Distance",
      "incorrect_answers": [
        "Birth By Sleep",
        "365/2 Days",
        "Re:Chain of Memories"
      ]
    },
    {
      "type": "multiple",
      "difficulty": "easy",
      "category": "Entertainment: Music",
      "question": "What was the best selling album of 2015?",
      "correct_answer": "Adele, 25",
      "incorrect_answers": [
        "Fetty Wap, Fetty Wap",
        "Taylor Swift, 1989",
        "Justin Bieber, Purpose"
      ]
    },
    {
      "type": "multiple",
      "difficulty": "easy",
      "category": "Entertainment: Film",
      "question": "Which of the following is not the name of a &quot;Bond Girl&quot;? ",
      "correct_answer": "Vanessa Kensington",
      "incorrect_answers": [
        "Pam Bouvier",
        "Mary Goodnight",
        "Wai Lin"
      ]
    },
    {
      "type": "multiple",
      "difficulty": "medium",
      "category": "Entertainment: Television",
      "question": "At which university do &quot;The Big Bang Theory&quot; characters Mr. Wolowitz and Drs. Cooper, Hofstadter and Koothrappali work?",
      "correct_answer": "Caltech",
      "incorrect_answers": [
        "UCLA",
        "MIT",
        "UC Berkeley "
      ]
    },
    {
      "type": "multiple",
      "difficulty": "hard",
      "category": "Entertainment: Japanese Anime &amp; Manga",
      "question": "In &quot;Highschool of the Dead&quot;, where did Komuro and Saeko establish to meet after the bus explosion?",
      "correct_answer": "Eastern Police Station",
      "incorrect_answers": [
        "The Center Mall",
        "Komuro&#039;s House",
        "On The Main Bridge"
      ]
    },
    {
      "type": "multiple",
      "difficulty": "hard",
      "category": "Entertainment: Video Games",
      "question": "How long was the World Record Speed Run of Valve Software&#039;s &quot;Half-Life&quot; that was done in 2014.",
      "correct_answer": "20 Minutes, 41 Seconds",
      "incorrect_answers": [
        "45 Minutes, 32 Seconds",
        "5 Minutes, 50 Seconds",
        "12 Minutes, 59 Seconds"
      ]
    },
    {
      "type": "multiple",
      "difficulty": "hard",
      "category": "Entertainment: Video Games",
      "question": "In the &quot;Halo&quot; series, what is the name of the race of aliens humans refer to as &quot;Grunts&quot;?",
      "correct_answer": "Unggoy",
      "incorrect_answers": [
        "Huragok",
        "Sangheili",
        "Yanme&#039;e"
      ]
    },
    {
      "type": "multiple",
      "difficulty": "hard",
      "category": "Entertainment: Television",
      "question": "Which of these Nickelodeon game shows aired first?",
      "correct_answer": "Double Dare",
      "incorrect_answers": [
        "Nick Arcade",
        "Finders Keepers",
        "Nickelodeon Guts"
      ]
    },
    {
      "type": "multiple",
      "difficulty": "medium",
      "category": "History",
      "question": "Who was the Prime Minister of the United Kingdom for most of World War II?",
      "correct_answer": "Winston Churchill",
      "incorrect_answers": [
        "Neville Chamberlain",
        "Harold Macmillan",
        "Edward Heath"
      ]
    },
    {
      "type": "multiple",
      "difficulty": "medium",
      "category": "Science: Computers",
      "question": "Which of these is the name for the failed key escrow device introduced by the National Security Agency in 1993?",
      "correct_answer": "Clipper Chip",
      "incorrect_answers": [
        "Enigma Machine",
        "Skipjack",
        "Nautilus"
      ]
    },
    {
      "type": "multiple",
      "difficulty": "medium",
      "category": "History",
      "question": "Joseph Stalin had a criminal past doing what?",
      "correct_answer": "Robbing Trains",
      "incorrect_answers": [
        "Murder for Hire",
        "Tax Evasion",
        "Identity Fraud"
      ]
    }
  ]
}