{
  "response_code": 0,
  "results": [
    {
      "type": "multiple",
      "difficulty": "easy",
      "category": "Entertainment: Music",
      "question": "&quot;The Singing Cowboy&quot; Gene Autry is credited with the first recording for all but which classic Christmas jingle?",
      "correct_answer": "White Christmas",
      "incorrect_answers": [
        "Frosty the Snowman",
        "Rudolph the Red-Nosed Reindeer",
        "Here Comes Santa Claus"
      ]
    },
    {
      "type": "multiple",
      "difficulty": "easy",
      "category": "General Knowledge",
      "question": "In the video-game franchise Kingdom Hearts, the main protagonist, carries a weapon with what shape?",
      "correct_answer": "Key",
      "incorrect_answers": [
        "Sword",
        "Pen",
        "Cellphone"
      ]
    },
    {
      "type": "multiple",
      "difficulty": "hard",
      "category": "Science &amp; Nature",
      "question": "What common name is given to the medial condition, tibial stress syndrome (MTSS)?",
      "correct_answer": "Shin Splints",
      "incorrect_answers": [
        "Tennis Elbow",
        "Carpal Tunnel",
        "Housemaid&#039;s Knee"
      ]
    },
    {
      "type": "multiple",
      "difficulty": "medium",
      "category": "Entertainment: Music",
      "question": "Which of the following guitarists recorded an album as a member of the Red Hot Chili Peppers?",
      "correct_answer": "Dave Navarro",
      "incorrect_answers": [
        "Tom Morello ",
        "Billy Corgan",
        "Ed O&#039;Brien"
      ]
    },
    {
      "type": "multiple",
      "difficulty": "hard",
      "category": "Entertainment: Video Games",
      "question": "Meryl Silverburgh, a video game character from the Metal Gear series, was originally a character in which game?",
      "correct_answer": "Policenauts",
      "incorrect_answers": [
        "Gradius",
        "Contra",
        "Castlevania: Symphony of the Night"
      ]
    },
    {
      "type": "multiple",
      "difficulty": "hard",
      "category": "Entertainment: Television",
      "question": "What was the callsign of Commander William Adama in Battlestar Galactica (2004)?",
      "correct_answer": "Husker",
      "incorrect_answers": [
        "Starbuck",
        "Apollo",
        "Crashdown"
      ]
    },
    {
      "type": "multiple",
      "difficulty": "easy",
      "category": "General Knowledge",
      "question": "When was the Playstation 3 released?",
      "correct_answer": "November 11, 2006",
      "incorrect_answers": [
        "January 8, 2007",
        "December 25, 2007",
        "July 16, 2006"
      ]
    },
    {
      "type": "multiple",
      "difficulty": "hard",
      "category": "History",
      "question": "What did the abbreviation &quot;RMS&quot; stand for in the RMS Titanic in 1912?",
      "correct_answer": "Royal Mail Ship",
      "incorrect_answers": [
        "Royal Majesty Service",
        "Regular Maritime Schedule ",
        "Regulated Maelstrom Sensor"
      ]
    },
    {
      "type": "multiple",
      "difficulty": "medium",
      "category": "Geography",
      "question": "How many timezones does Russia have?",
      "correct_answer": "11",
      "incorrect_answers": [
        "6",
        "24",
        "16"
      ]
    },
    {
      "type": "multiple",
      "difficulty": "medium",
      "category": "Entertainment: Music",
      "question": "Who had a US and UK number 1 hit in 1962 with the instrumental, &#039;Telstar&#039;?",
      "correct_answer": "The Tornados",
      "incorrect_answers": [
        "The Ventures",
        "The Spotnicks",
        "The Tremeloes"
      ]
    },
    {
      "type": "multiple",
      "difficulty": "easy",
      "category": "History",
      "question": "What was the name commonly given to the ancient trade routes that connected the East and West of Eurasia?",
      "correct_answer": "Silk Road",
      "incorrect_answers": [
        "Spice Road",
        "Clay Road",
        "Salt Road"
      ]
    },
    {
      "type": "multiple",
      "difficulty": "medium",
      "category": "General Knowledge",
      "question": "What is the Italian word for &quot;tomato&quot;?",
      "correct_answer": "Pomodoro",
      "incorrect_answers": [
        "Aglio",
        "Cipolla",
        "Peperoncino"
      ]
    },
    {
      "type": "multiple",
      "difficulty": "medium",
      "category": "Entertainment: Video Games",
      "question": "In the Mario series, which game introduced Mario&#039;s Backflip ability?",
      "correct_answer": "Donkey Kong (Gameboy)",
      "incorrect_answers": [
        "Super Mario 64",
        "Super Mario 3D Land",
        "Super Mario Galaxy"
      ]
    },
    {
      "type": "multiple",
      "difficulty": "medium",
      "category": "History",
      "question": "The minigun was designed in 1960 by which manufacturer.",
      "correct_answer": "General Electric",
      "incorrect_answers": [
        "Colt Firearms",
        "Heckler &amp; Koch",
        "Sig Sauer"
      ]
    },
    {
      "type": "multiple",
      "difficulty": "medium",
      "category": "History",
      "question": "What date was the first flight of the P-40 Warhawk?",
      "correct_answer": "October 14 1938",
      "incorrect_answers": [
        "August 21 1939",
        "January 12 1940",
        "June 1 1939"
      ]
    },
    {
      "type": "multiple",
      "difficulty": "medium",
      "category": "General Knowledge",
      "question": "In what year did Halley&#039;s Comet, which will not appear again until the year 2061, previously approach Earth?",
      "correct_answer": "1986",
      "incorrect_answers": [
        "2001",
        "1942",
        "1909"
      ]
    },
    {
      "type": "multiple",
      "difficulty": "easy",
      "category": "History",
      "question": "Which of the following ancient peoples was NOT classified as Hellenic (Greek)?",
      "correct_answer": "Illyrians",
      "incorrect_answers": [
        "Dorians",
        "Achaeans",
        "Ionians"
      ]
    },
    {
      "type": "multiple",
      "difficulty": "medium",
      "category": "Celebrities",
      "question": "What was the cause of death for Freddie Mercury?",
      "correct_answer": "Pneumonia",
      "incorrect_answers": [
        "Stomach Cancer",
        "HIV",
        "Brain Hemorrhage"
      ]
    },
    {
      "type": "multiple",
      "difficulty": "medium",
      "category": "Entertainment: Film",
      "question": "What were the Chilled Monkey Brains made from during Indiana Jones and the Temple of Doom?",
      "correct_answer": "Custard and Raspberry Sauce",
      "incorrect_answers": [
        "Strawberry Ice Cream",
        "Cherry Yogurt",
        "Raspberry Sorbet"
      ]
    },
    {
      "type": "multiple",
      "difficulty": "medium",
      "category": "Sports",
      "question": "Which team was the 2014-2015 NBA Champions?",
      "correct_answer": "Golden State Warriors",
      "incorrect_answers": [
        "Cleveland Cavaliers",
        "Houston Rockets",
        "Atlanta Hawks"
      ]
    },
    {
      "type": "multiple",
      "difficulty": "medium",
      "category": "History",
      "question": "Which Louis was known as &#039;The Sun King of France&#039;?",
      "correct_answer": "Louis XIV",
      "incorrect_answers": [
        "Louis XIII",
        "Louis XV",
        "Louis XVI"
      ]
    },
    {
      "type": "multiple",
      "difficulty": "hard",
      "category": "General Knowledge",
      "question": "According to Fair Works Australia, how long do you have to work to get Long Service Leave?",
      "correct_answer": "7 years",
      "incorrect_answers": [
        "2 years",
        "8 years",
        "6 months"
      ]
    },
    {
      "type": "multiple",
      "difficulty": "easy",
      "category": "Entertainment: Film",
      "question": "The 2016 Disney animated film &#039;Moana&#039; is based on which culture?",
      "correct_answer": "Polynesian",
      "incorrect_answers": [
        "Native American",
        "Japanese",
        "Nordic"
      ]
    },
    {
      "type": "multiple",
      "difficulty": "medium",
      "category": "Entertainment: Film",
      "question": "In the 1971 film &quot;Willy Wonka &amp; the Chocolate Factory&quot;, who played Willy Wonka?",
      "correct_answer": "Gene Wilder",
      "incorrect_answers": [
        "Shia LeBouf",
        "Peter Ostrum",
        "Johnny Depp"
      ]
    },
    {
      "type": "multiple",
      "difficulty": "easy",
      "category": "Animals",
      "question": "What is the name of a rabbit&#039;s abode?",
      "correct_answer": "Burrow",
      "incorrect_answers": [
        "Nest",
        "Den",
        "Dray"
      ]
    },
    {
      "type": "multiple",
      "difficulty": "medium",
      "category": "Science &amp; Nature",
      "question": "In human biology, a circadium rhythm relates to a period of roughly how many hours?",
      "correct_answer": "24",
      "incorrect_answers": [
        "8",
        "16",
        "32"
      ]
    },
    {
      "type": "multiple",
      "difficulty": "medium",
      "category": "Vehicles",
      "question": "When was Cadillac founded?",
      "correct_answer": "1902",
      "incorrect_answers": [
        "1964",
        "1898",
        "1985"
      ]
    },
    {
      "type": "multiple",
      "difficulty": "easy",
      "category": "Geography",
      "question": "If soccer is called football in England, what is American football called in England?",
      "correct_answer": "American football",
      "incorrect_answers": [
        "Combball",
        "Handball",
        "Touchdown"
      ]
    },
    {
      "type": "multiple",
      "difficulty": "easy",
      "category": "Entertainment: Video Games",
      "question": "How many times do you fight Gilgamesh in &quot;Final Fantasy 5&quot;?",
      "correct_answer": "6",
      "incorrect_answers": [
        "4",
        "5",
        "3"
      ]
    },
    {
      "type": "multiple",
      "difficulty": "easy",
      "category": "Entertainment: Film",
      "question": "Who plays protagonist Ethan Hunt in the &quot;Mission: Impossible&quot; film-series?",
      "correct_answer": "Tom Cruise",
      "incorrect_answers": [
        "Johnny Depp",
        "Sean Connery",
        "Pierce Brosnan"
      ]
    },
    {
      "type": "multiple",
      "difficulty": "easy",
      "category": "Entertainment: Television",
      "question": "When did the TV show Rick and Morty first air on Adult Swim?",
      "correct_answer": "2013",
      "incorrect_answers": [
        "2014",
        "2016",
        "2015"
      ]
    },
    {
      "type": "multiple",
      "difficulty": "medium",
      "category": "Entertainment: Video Games",
      "question": "Which of these weapons is NOT available to the Terrorist team in the game, &quot;Counter-Strike: Global Offensive&quot;?",
      "correct_answer": "SCAR-20",
      "incorrect_answers": [
        "SG 550",
        "CZ-75",
        "XM1014"
      ]
    },
    {
      "type": "multiple",
      "difficulty": "medium",
      "category": "General Knowledge",
      "question": "What is the currency of Poland?",
      "correct_answer": "Złoty",
      "incorrect_answers": [
        "Ruble",
        "Euro",
        "Krone"
      ]
    },
    {
      "type": "multiple",
      "difficulty": "hard",
      "category": "Entertainment: Video Games",
      "question": "What Touhou Project character&#039;s first ever appearance was as a midboss in the eighth game, Imperishable Night?",
      "correct_answer": "Tewi Inaba",
      "incorrect_answers": [
        "Mystia Lorelei",
        "Kaguya Houraisan",
        "Rumia"
      ]
    },
    {
      "type": "multiple",
      "difficulty": "medium",
      "category": "Entertainment: Video Games",
      "question": "When was Final Fantasy XV released?",
      "correct_answer": "November 29th, 2016",
      "incorrect_answers": [
        "October 25th, 2016",
        "December 31th, 2016",
        "November 30th, 2016"
      ]
    },
    {
      "type": "multiple",
      "difficulty": "easy",
      "category": "Entertainment: Film",
      "question": "This movie contains the quote, &quot;Houston, we have a problem.&quot;",
      "correct_answer": "Apollo 13",
      "incorrect_answers": [
        "The Right Stuff",
        "Capricorn One",
        "Marooned"
      ]
    },
    {
      "type": "multiple",
      "difficulty": "hard",
      "category": "Entertainment: Books",
      "question": "Which author and poet famously wrote the line, &quot;The female of the species is more deadly than the male&quot;?",
      "correct_answer": "Rudyard Kipling",
      "incorrect_answers": [
        "Edgar Allan Poe",
        "William Shakespeare",
        "William Wordsworth"
      ]
    },
    {
      "type": "multiple",
      "difficulty": "medium",
      "category": "Geography",
      "question": "What is the right way to spell the capital of Hungary?",
      "correct_answer": "Budapest",
      "incorrect_answers": [
        "Boodapest",
        "Bhudapest",
        "Budapast"
      ]
    },
    {
      "type": "multiple",
      "difficulty": "medium",
      "category": "Entertainment: Film",
      "question": "What film did James Cameron&#039;s Avatar dethrone as the highest-grossing film ever?",
      "correct_answer": "Titanic",
      "incorrect_answers": [
        "Star Wars",
        "Gone with the Wind",
        "Jaws"
      ]
    },
    {
      "type": "multiple",
      "difficulty": "medium",
      "category": "Entertainment: Film",
      "question": "Actress Susan Sarandon caught pneumonia during filming of which movie?",
      "correct_answer": "The Rocky Horror Picture Show",
      "incorrect_answers": [
        "Thelma and Louise",
        "Dead Man Walking",
        "Enchanted"
      ]
    },
    {
      "type": "multiple",
      "difficulty": "hard",
      "category": "General Knowledge",
      "question": "Which product did Nokia, the telecommunications company, originally sell?",
      "correct_answer": "Paper",
      "incorrect_answers": [
        "Phones",
        "Computers",
        "Processors"
      ]
    },
    {
      "type": "multiple",
      "difficulty": "medium",
      "category": "Entertainment: Video Games",
      "question": "What snowy mob was added in Minecraft 1.10?",
      "correct_answer": "Polar bears",
      "incorrect_answers": [
        "Eskimos",
        "Penguins",
        "Walking TNT"
      ]
    },
    {
      "type": "multiple",
      "difficulty": "easy",
      "category": "Entertainment: Television",
      "question": "On the NBC show Community, whose catch-phrase was &quot;Pop! Pop!&quot;?",
      "correct_answer": "Magnitude",
      "incorrect_answers": [
        "Star Burns",
        "Leonard",
        "Senoir Chang"
      ]
    },
    {
      "type": "multiple",
      "difficulty": "medium",
      "category": "General Knowledge",
      "question": "Which of these American singers and songwriters won a Nobel Prize in Literature?",
      "correct_answer": "Bob Dylan",
      "incorrect_answers": [
        "Buddy Holly",
        "Johnny Cash",
        "Alice Cooper"
      ]
    },
    {
      "type": "multiple",
      "difficulty": "medium",
      "category": "Entertainment: Film",
      "question": "In the 1994 movie &quot;Speed&quot;, what is the minimum speed the bus must go to prevent to bomb from exploding?",
      "correct_answer": "50 mph",
      "incorrect_answers": [
        "60 mph",
        "40 mph",
        "70 mph"
      ]
    },
    {
      "type": "multiple",
      "difficulty": "easy",
      "category": "History",
      "question": "Which of these countries remained neutral during World War II?",
      "correct_answer": "Switzerland",
      "incorrect_answers": [
        "United Kingdom",
        "France",
        "Italy"
      ]
    },
    {
      "type": "multiple",
      "difficulty": "easy",
      "category": "Entertainment: Television",
      "question": "In the show &quot;Futurama&quot; what is Fry&#039;s full name?",
      "correct_answer": "Philip J. Fry",
      "incorrect_answers": [
        "Fry J. Philip",
        "Fry Rodr&iacute;guez",
        "Fry Philip"
      ]
    },
    {
      "type": "multiple",
      "difficulty": "hard",
      "category": "History",
      "question": "Toussaint Louverture led a successful slave revolt in which country?",
      "correct_answer": "Haiti",
      "incorrect_answers": [
        "France",
        "Cuba",
        "United States"
      ]
    },
    {
      "type": "multiple",
      "difficulty": "medium",
      "category": "General Knowledge",
      "question": "What does the &quot;G&quot; mean in &quot;G-Man&quot;?",
      "correct_answer": "Government",
      "incorrect_answers": [
        "Going",
        "Ghost",
        "Geronimo"
      ]
    },
    {
      "type": "multiple",
      "difficulty": "hard",
      "category": "General Knowledge",
      "question": "Disney&#039;s Haunted Mansion is home to a trio of Hitchhiking Ghosts. Which of these is NOT one of them?",
      "correct_answer": "Harry",
      "incorrect_answers": [
        "Gus",
        "Phineas",
        "Ezra"
      ]
    }
  ]
}