{
  "response_code": 0,
  "results": [
    {
      "type": "multiple",
      "difficulty": "hard",
      "category": "Science: Gadgets",
      "question": "Who built the first laser?",
      "correct_answer": "Theodore Harold Maiman",
      "incorrect_answers": [
        "Nikola Tesla",
        "Jack Kilby",
        "Edith Clarke"
      ]
    },
    {
      "type": "multiple",
      "difficulty": "medium",
      "category": "History",
      "question": "Which Nazi General was known as the &quot;Desert Fox&quot;?",
      "correct_answer": "Erwin Rommel",
      "incorrect_answers": [
        "Gerd von Rundstadt",
        "Wilhelm Keitel",
        "Heinz Guderian "
      ]
    },
    {
      "type": "multiple",
      "difficulty": "hard",
      "category": "Geography",
      "question": "How many stations does the Central Line have on the London Underground?",
      "correct_answer": "49",
      "incorrect_answers": [
        "51",
        "43",
        "47"
      ]
    },
    {
      "type": "multiple",
      "difficulty": "medium",
      "category": "Entertainment: Video Games",
      "question": "Which of these is NOT a name of a playable character in Apex Legends?",
      "correct_answer": "Viper",
      "incorrect_answers": [
        "Revenant",
        "Crypto",
        "Wattson"
      ]
    },
    {
      "type": "multiple",
      "difficulty": "hard",
      "category": "Politics",
      "question": "Which major bank&#039;s collapse was notable as one of the causes of the Financal Crisis of 2008?",
      "correct_answer": "Lehman Brothers",
      "incorrect_answers": [
        "HSBC",
        "Barclays",
        "Lloyds"
      ]
    },
    {
      "type": "multiple",
      "difficulty": "easy",
      "category": "Entertainment: Music",
      "question": "Which rap group released the album &quot;Straight Outta Compton&quot;?",
      "correct_answer": "N.W.A",
      "incorrect_answers": [
        "Wu-Tang Clan",
        "Run-D.M.C.",
        "Beastie Boys"
      ]
    },
    {
      "type": "multiple",
      "difficulty": "medium",
      "category": "Entertainment: Video Games",
      "question": "Who created the pump &quot;F.L.U.D.D.&quot; Mario uses in Super Mario Sunshine?",
      "correct_answer": "Elvin Gadd",
      "incorrect_answers": [
        "Robert Fludd",
        "Nirona",
        "Crygor"
      ]
    },
    {
      "type": "multiple",
      "difficulty": "easy",
      "category": "Entertainment: Video Games",
      "question": "Which of the following is NOT a summon in the game &quot;South Park: The Stick of Truth&quot;?",
      "correct_answer": "Towelie",
      "incorrect_answers": [
        "Jesus",
        "Mr. Hankey",
        "Mr. Slave"
      ]
    },
    {
      "type": "multiple",
      "difficulty": "easy",
      "category": "Entertainment: Music",
      "question": "What is the stage name of English female rapper Mathangi Arulpragasam, who is known for the song &quot;Paper Planes&quot;?",
      "correct_answer": "M.I.A.",
      "incorrect_answers": [
        "K.I.A.",
        "C.I.A.",
        "A.I.A."
      ]
    },
    {
      "type": "multiple",
      "difficulty": "medium",
      "category": "Entertainment: Film",
      "question": "What is the name of the villian in the 2015 Russian-American Sci-Fi Movie &quot;Hardcore Henry&quot;?",
      "correct_answer": "Akan",
      "incorrect_answers": [
        "Estelle",
        "Jimmy",
        "Henry"
      ]
    },
    {
      "type": "multiple",
      "difficulty": "medium",
      "category": "Entertainment: Cartoon &amp; Animations",
      "question": "Which city did Anger berate for ruining pizza in &quot;Inside Out&quot;?",
      "correct_answer": "San Francisco",
      "incorrect_answers": [
        "Minnesota",
        "Washington",
        "California"
      ]
    },
    {
      "type": "multiple",
      "difficulty": "hard",
      "category": "Sports",
      "question": "Which year was the third Super Bowl held?",
      "correct_answer": "1969",
      "incorrect_answers": [
        "1968",
        "1971",
        "1970"
      ]
    },
    {
      "type": "multiple",
      "difficulty": "hard",
      "category": "Science &amp; Nature",
      "question": "What is the molecular formula of Ozone?",
      "correct_answer": "O3",
      "incorrect_answers": [
        "C6H2O6",
        "N2O",
        "SO4"
      ]
    },
    {
      "type": "multiple",
      "difficulty": "medium",
      "category": "Entertainment: Musicals &amp; Theatres",
      "question": "In which Shakespeare play does the character Marcellus say, &quot;Something is rotten in the state of Denmark&quot;?",
      "correct_answer": "Hamlet",
      "incorrect_answers": [
        "Macbeth",
        "King Lear",
        "Twelfth Night"
      ]
    },
    {
      "type": "multiple",
      "difficulty": "hard",
      "category": "Entertainment: Film",
      "question": "Which actress portrayed Dr. Grace Augustine in the James Cameron movie &quot;Avatar&quot;?",
      "correct_answer": "Sigourney Weaver",
      "incorrect_answers": [
        "Jessica Chastain",
        "Melissa Beckett",
        "Alyssa Monroe "
      ]
    },
    {
      "type": "multiple",
      "difficulty": "easy",
      "category": "General Knowledge",
      "question": "The file hosting service, &quot;Google Drive&quot; was launched on what day?",
      "correct_answer": "April 24, 2012",
      "incorrect_answers": [
        "January 12, 2014",
        "November 14, 2008",
        "January 20, 2010"
      ]
    },
    {
      "type": "multiple",
      "difficulty": "medium",
      "category": "Entertainment: Japanese Anime &amp; Manga",
      "question": "In the &quot;Re:Zero&quot; manga series, which of the following Sin Archbishops eats Rem&#039;s existence?",
      "correct_answer": "Ley Batenkaitos",
      "incorrect_answers": [
        "Roy Alphard",
        "Petelgeuse Romanee-Conti",
        "Louis Arneb"
      ]
    },
    {
      "type": "multiple",
      "difficulty": "medium",
      "category": "Entertainment: Video Games",
      "question": "In &quot;PAYDAY 2&quot;, what weapon has the highest base weapon damage on a per-shot basis?",
      "correct_answer": "HRL-7",
      "incorrect_answers": [
        "Heavy Crossbow",
        "Thanatos .50 cal",
        "Broomstick Pistol"
      ]
    },
    {
      "type": "multiple",
      "difficulty": "easy",
      "category": "Science &amp; Nature",
      "question": "Which gas forms about 78% of the Earth&rsquo;s atmosphere?",
      "correct_answer": "Nitrogen",
      "incorrect_answers": [
        "Oxygen",
        "Argon",
        "Carbon Dioxide"
      ]
    },
    {
      "type": "multiple",
      "difficulty": "medium",
      "category": "Geography",
      "question": "What is the capital city of Slovenia?",
      "correct_answer": "Ljubljana",
      "incorrect_answers": [
        "Maribor",
        "Velenje",
        "Trbovlje"
      ]
    },
    {
      "type": "multiple",
      "difficulty": "hard",
      "category": "Entertainment: Comics",
      "question": "What is the real hair colour of the mainstream comic book version (Earth-616) of Daredevil?",
      "correct_answer": "Blonde",
      "incorrect_answers": [
        "Auburn",
        "Brown",
        "Black"
      ]
    },
    {
      "type": "multiple",
      "difficulty": "medium",
      "category": "Geography",
      "question": "All of the following countries have official claims to territory in Antartica EXCEPT:",
      "correct_answer": "United States",
      "incorrect_answers": [
        "Australia",
        "Chile",
        "Norway"
      ]
    },
    {
      "type": "multiple",
      "difficulty": "hard",
      "category": "Sports",
      "question": "Where was the Games of the XXII Olympiad held?",
      "correct_answer": "Moscow",
      "incorrect_answers": [
        "Barcelona",
        "Tokyo",
        "Los Angeles"
      ]
    },
    {
      "type": "multiple",
      "difficulty": "medium",
      "category": "Entertainment: Music",
      "question": "How many members are in the Japanese rock band SCANDAL?",
      "correct_answer": "4",
      "incorrect_answers": [
        "5",
        "2",
        "18"
      ]
    },
    {
      "type": "multiple",
      "difficulty": "hard",
      "category": "Entertainment: Music",
      "question": "What is the name of the song by Beyonc&eacute; and Alejandro Fern&aacute;ndez released in 2007?",
      "correct_answer": "Amor Gitano",
      "incorrect_answers": [
        "La ultima vez",
        "Rocket",
        "Hasta Dondes Estes"
      ]
    },
    {
      "type": "multiple",
      "difficulty": "medium",
      "category": "Entertainment: Music",
      "question": "When did The Beatles release the LP &quot;Please Please Me&quot;?",
      "correct_answer": "1963",
      "incorrect_answers": [
        "1970",
        "1960",
        "1969"
      ]
    },
    {
      "type": "multiple",
      "difficulty": "hard",
      "category": "Entertainment: Board Games",
      "question": "Which of these cards from &quot;Magic: The Gathering&quot; has a flavor text that begins with &quot;Oi oi oi&quot;?",
      "correct_answer": "Uthden Troll",
      "incorrect_answers": [
        "Lotleth Troll",
        "Albino Troll",
        "Harvester Troll"
      ]
    },
    {
      "type": "multiple",
      "difficulty": "easy",
      "category": "Entertainment: Comics",
      "question": "Who is Batman?",
      "correct_answer": "Bruce Wayne",
      "incorrect_answers": [
        "Clark Kent",
        "Barry Allen",
        "Tony Stark"
      ]
    },
    {
      "type": "multiple",
      "difficulty": "easy",
      "category": "General Knowledge",
      "question": "In the video-game franchise Kingdom Hearts, the main protagonist, carries a weapon with what shape?",
      "correct_answer": "Key",
      "incorrect_answers": [
        "Sword",
        "Pen",
        "Cellphone"
      ]
    },
    {
      "type": "multiple",
      "difficulty": "easy",
      "category": "Entertainment: Music",
      "question": "What 1970&#039;s American ballad referred to the 1959 plane crash as the &quot;the day the music died&quot;?",
      "correct_answer": "American Pie",
      "incorrect_answers": [
        "Kentucky Rain",
        "I Will Always Love You",
        "Rock &#039;n&#039; Roll Suicide"
      ]
    },
    {
      "type": "multiple",
      "difficulty": "medium",
      "category": "Sports",
      "question": "How many premier league trophies did Sir Alex Ferguson win during his time at Manchester United?",
      "correct_answer": "13",
      "incorrect_answers": [
        "11",
        "20",
        "22"
      ]
    },
    {
      "type": "multiple",
      "difficulty": "hard",
      "category": "Animals",
      "question": "What was the name of the Ethiopian Wolf before they knew it was related to wolves?",
      "correct_answer": "Simien Jackel",
      "incorrect_answers": [
        "Ethiopian Coyote",
        "Amharic Fox",
        "Canis Simiensis"
      ]
    },
    {
      "type": "multiple",
      "difficulty": "medium",
      "category": "History",
      "question": "In what year did the North American Video Game Crash occur?",
      "correct_answer": "1983",
      "incorrect_answers": [
        "1982",
        "1993",
        "1970"
      ]
    },
    {
      "type": "multiple",
      "difficulty": "easy",
      "category": "Entertainment: Video Games",
      "question": "In &quot;World of Warcraft,&quot; which of the following can be found outside of every instanced dungeon?",
      "correct_answer": "A Meeting Stone",
      "incorrect_answers": [
        "A Summoning Stone",
        "A Gathering Stone",
        "A Hearthstone"
      ]
    },
    {
      "type": "multiple",
      "difficulty": "easy",
      "category": "Entertainment: Music",
      "question": "What was the subject of the 2014 song &quot;CoCo&quot; by American rapper O. T. Genasis?",
      "correct_answer": "Cocaine",
      "incorrect_answers": [
        "Conan O&#039;Brien",
        "Cobalt(II) carbonate",
        "Coconut cream pie"
      ]
    },
    {
      "type": "multiple",
      "difficulty": "medium",
      "category": "Science: Computers",
      "question": "What was the name given to Android 4.3?",
      "correct_answer": "Jelly Bean",
      "incorrect_answers": [
        "Lollipop",
        "Nutella",
        "Froyo"
      ]
    },
    {
      "type": "multiple",
      "difficulty": "medium",
      "category": "Entertainment: Japanese Anime &amp; Manga",
      "question": "What is the name of the infamous pachinko machine from &quot;Kaiji&quot;?",
      "correct_answer": "The Bog",
      "incorrect_answers": [
        "The Devil",
        "The Undefeated",
        "The Dragon"
      ]
    },
    {
      "type": "multiple",
      "difficulty": "easy",
      "category": "Entertainment: Video Games",
      "question": "Which company did Gabe Newell work at before founding Valve Corporation?",
      "correct_answer": "Microsoft",
      "incorrect_answers": [
        "Apple",
        "Google",
        "Yahoo"
      ]
    },
    {
      "type": "multiple",
      "difficulty": "hard",
      "category": "Entertainment: Film",
      "question": "In &quot;Star Trek Nemesis&quot;, why was Praetor Shinzon created?",
      "correct_answer": "To replace Picard as a Romulan Agent",
      "incorrect_answers": [
        "To destroy the Enterprise",
        "To become Picard&#039;s friend ",
        "To steal the Enterprise"
      ]
    },
    {
      "type": "multiple",
      "difficulty": "easy",
      "category": "Entertainment: Music",
      "question": "How many members are there in the band Nirvana?",
      "correct_answer": "Three",
      "incorrect_answers": [
        "Two",
        "Four",
        "Five"
      ]
    },
    {
      "type": "multiple",
      "difficulty": "easy",
      "category": "Entertainment: Video Games",
      "question": "What is the maximum HP in Terraria?",
      "correct_answer": "500",
      "incorrect_answers": [
        "400",
        "1000",
        "100"
      ]
    },
    {
      "type": "multiple",
      "difficulty": "easy",
      "category": "Art",
      "question": "Which painting was not made by Vincent Van Gogh?",
      "correct_answer": "The Ninth Wave",
      "incorrect_answers": [
        "Caf&eacute; Terrace at Night",
        "Bedroom In Arles",
        "Starry Night"
      ]
    },
    {
      "type": "multiple",
      "difficulty": "hard",
      "category": "General Knowledge",
      "question": "Which of the following languages does NOT use gender as a part of its grammar?",
      "correct_answer": "Turkish",
      "incorrect_answers": [
        "German",
        "Danish",
        "Polish"
      ]
    },
    {
      "type": "multiple",
      "difficulty": "medium",
      "category": "Entertainment: Japanese Anime &amp; Manga",
      "question": "In Pok&eacute;mon Chronicles, why was Misty afraid of Gyarados?",
      "correct_answer": "She crawled into it&#039;s mouth as a baby.",
      "incorrect_answers": [
        "She found it scary.",
        "She was badly injured from it.",
        "It is part Bug."
      ]
    },
    {
      "type": "multiple",
      "difficulty": "medium",
      "category": "General Knowledge",
      "question": "What is the name of the very first video uploaded to YouTube?",
      "correct_answer": "Me at the zoo",
      "incorrect_answers": [
        "tribute",
        "carrie rides a truck",
        "Her new puppy from great grandpa vern."
      ]
    },
    {
      "type": "multiple",
      "difficulty": "medium",
      "category": "Animals",
      "question": "What is the collective noun for rats?",
      "correct_answer": "Mischief",
      "incorrect_answers": [
        "Pack",
        "Race",
        "Drift"
      ]
    },
    {
      "type": "multiple",
      "difficulty": "medium",
      "category": "General Knowledge",
      "question": "In a standard set of playing cards, which is the only king without a moustache?",
      "correct_answer": "Hearts",
      "incorrect_answers": [
        "Spades",
        "Diamonds",
        "Clubs"
      ]
    },
    {
      "type": "multiple",
      "difficulty": "medium",
      "category": "Geography",
      "question": "The land mass of modern day Turkey is called what?",
      "correct_answer": "Anatolia",
      "incorrect_answers": [
        "Ismuth of Ottoma",
        "Ottoma",
        "Ismuth of Anatolia"
      ]
    },
    {
      "type": "multiple",
      "difficulty": "medium",
      "category": "Entertainment: Video Games",
      "question": "What is the mod &quot;Cry of Fear&quot; based off of?",
      "correct_answer": "Half-Life",
      "incorrect_answers": [
        "Counter Strike: Source",
        "Half-Life 2",
        "It&#039;s a stand alone game, not a mod"
      ]
    },
    {
      "type": "multiple",
      "difficulty": "hard",
      "category": "Entertainment: Television",
      "question": "What is the name of the pirate that sings the intro to &quot;Spongebob Squarepants&quot;?",
      "correct_answer": "Painty",
      "incorrect_answers": [
        "Patchy",
        "Lloyd",
        "Larry"
      ]
    }
  ]
}